[{"id": "47679797", "keyword": "bag", "image_url": "https://target.scene7.com/is/image/Target/GUEST_b66d5835-b832-4de8-b0b5-067b49c0bfd8", "title": "Target Reusable Tote Bag", "price": "$0.99", "description": ["Target reusable shopping bag sports an allover bullseye design", "Sturdy nonwoven construction for lasting use", "Double top handles allow for easy carrying", "Side loops let you put it on the bag holder at checkout", "16.5in. (H) x 12in. (W) x 7in. (D)"]}, {"id": "76557206", "keyword": "bag", "image_url": "https://target.scene7.com/is/image/Target/GUEST_9fcf9944-5025-4716-aaa3-cff6c84d8392", "title": "Reusable Bag", "price": "$1.99", "description": ["Reusable bag is a convenient shopping companion", "Two long handles make for easy carrying", "Soft construction lets you fit a variety of items", "Durable fabric ensures lasting, reliable use"], "image_backup": ["https://target.scene7.com/is/image/Target/GUEST_6db7d48b-d1c2-40ee-a0e9-129b47fd123c"]}, {"id": "84188993", "keyword": "bag", "image_url": "https://target.scene7.com/is/image/Target/GUEST_06a2b87a-3225-42f7-b834-b5acb7510abe", "title": "Vera Bradley Womens Recycled Cotton RFID All in One Crossbody Bag Butterfly By", "price_range": "$45.50 - $65.00", "price": "$65.00", "description": ["Consciously crafted with recycled cotton", "Shop Vera Bradley for top gifts for women. Graduation, birthdays, Christmas and Mothers Day, we have all of the options youre searching for to make her smile", "Vera Bradley is a destination for Tote Bags, Travel Styles, Backpacks and Accessories for women", "Interior features 10 card slips, four slip pockets, one bill pocket, one interior back compartment pocket and one ID window", "Zip and magnetic closures."], "image_backup": ["https://target.scene7.com/is/image/Target/GUEST_42ff0beb-d78c-4e1e-a045-fdfab97d6b5b", "https://target.scene7.com/is/image/Target/GUEST_8322812c-10b0-4f95-94ef-7f11573727a5", "https://target.scene7.com/is/image/Target/GUEST_ea6000c5-71f7-4730-ba3c-1250062692ab"]}, {"id": "51519648", "keyword": "bag", "image_url": "https://target.scene7.com/is/image/Target/GUEST_c5407a89-a2ca-4b02-9cc1-d18e4fd57b43", "title": "Small Gift Bag Pink - Spritz&#8482;", "price": "$1.50", "description": ["Paper gift bag keeps gifting easy", "Soft pink color adds a sweet style", "Perfect for smaller gifts"]}, {"id": "51519699", "keyword": "bag", "image_url": "https://target.scene7.com/is/image/Target/GUEST_9b17e075-f8e3-44d5-88b7-05cce271fbdf", "title": "Large Polka Dots Gift Bag Pink - Spritz&#8482;", "price": "$3.00", "description": ["Paper gift bag keeps gifting easy", "White triangles add a whimsical style", "Large enough for a wide variety of gifts"]}, {"id": "81549579", "keyword": "bag", "image_url": "https://target.scene7.com/is/image/Target/GUEST_3e7f0d22-320c-4841-be3e-64d526c862d7", "title": "Paxton Tote Handbag - Universal Thread&#8482; Olive Green", "price_range": "$21.25 - $25.00", "price": "$25.00", "description": ["Universal Thread tote bag is perfect for everyday errands and carrying", "Beautiful floral print pattern with contrasting solid handles and strap", "Main compartment and multiple pockets offer ample space for your everyday essentials", "Top zipper closure on main compartment keeps your items neatly inside", "Adjustable/removable shoulder strap so you can carry as a crossbody if desired"], "image_backup": ["https://target.scene7.com/is/image/Target/GUEST_03ba1964-d3b2-42f4-99c7-ca00353afb05", "https://target.scene7.com/is/image/Target/GUEST_39c25d4f-c588-4ddd-826f-c9d5d4850e16"]}, {"id": "81911211", "keyword": "bag", "image_url": "https://target.scene7.com/is/image/Target/GUEST_85b755b0-927f-4f0b-8588-328ee5708326", "title": "Kipling Abanu Multi Metallic Convertible Crossbody Bag Metallic Glow", "price_range": "$55.30", "price": "$55.30", "description": ["Nylon", "Dimensions: 7.5L x 5H x 3.25D", "Weight: 0.62 lbs", "Volume: 2L", "Two main zip compartments"], "image_backup": ["https://target.scene7.com/is/image/Target/GUEST_6ab50c2c-c85c-4b1b-9f81-d9cb8c75bf52", "https://target.scene7.com/is/image/Target/GUEST_daa3696d-edc8-4ce4-aef5-66dd4b8ae4a2", "https://target.scene7.com/is/image/Target/GUEST_69bd87ed-1557-4e6e-b92b-f0389d2d41b8"]}, {"id": "77569863", "keyword": "bag", "image_url": "https://target.scene7.com/is/image/Target/GUEST_ff834611-e928-44bc-be85-4016a2a1d2b1", "title": "Mesh Tote Handbag - Shade &#38; Shore&#8482; Black", "price_range": "$10.00", "price": "$10.00", "description": ["Mesh tote handbag offers an easy, see-through design", "Main compartment and side pockets offer ample space for your items", "Open top helps provide easy access to your items", "Double loop handles make carrying it easier"], "image_backup": ["https://target.scene7.com/is/image/Target/GUEST_7d401dd6-ba45-4540-90c9-e79248807e7d"]}, {"id": "81068090", "keyword": "bag", "image_url": "https://target.scene7.com/is/image/Target/GUEST_e193d344-3054-4179-87b5-7007a9089c96", "title": "Small Reusable Fabric Dots Gift Bag - Spritz&#8482;", "price": "$3.00", "description": ["Add a touch of color and cuteness to your gift", "Perfect for a variety of occasions", "Cotton fabric bag", "Reusable"], "image_backup": ["https://target.scene7.com/is/image/Target/GUEST_a0a85336-3d4c-4407-8107-d05c1f3ac604", "https://target.scene7.com/is/image/Target/GUEST_20f16028-7f91-47a8-94c4-af266a9d7620"]}, {"id": "80968264", "keyword": "bag", "image_url": "https://target.scene7.com/is/image/Target/GUEST_989c302c-2ae6-462f-90fd-b6541174f397", "title": "Value Crossbody Bag - Wild Fable&#8482; Black", "price_range": "$12.00", "price": "$12.00", "description": ["Faux-leather crossbody bag", "Flap zip closure opens up to 2 compartments", "Comes in a solid color", "Adjustable strap for comfortable carrying"], "image_backup": ["https://target.scene7.com/is/image/Target/GUEST_4212cf38-79f6-4119-b716-744c37975c62", "https://target.scene7.com/is/image/Target/GUEST_7ef82d65-cc9c-404e-940a-f1f52ffb8fbd"]}, {"id": "16612436", "keyword": "bag", "image_url": "https://target.scene7.com/is/image/Target/GUEST_1344cf70-5c92-4bae-a5f5-087009926213", "title": "Large Gift Bag Navy - Spritz&#8482;", "price": "$3.00", "description": ["Large blue gift bag", "Perfect for baby showers, birthdays and more", "Add matching tissue paper for a classy finish"]}, {"id": "77377107", "keyword": "bag", "image_url": "https://target.scene7.com/is/image/Target/GUEST_bf03b5e0-f6ed-45d2-b650-64c4770cb993", "title": "Burst Print Foldable Tote Bag - Black", "price": "$2.99", "description": ["Fold-up tote bag makes it easy to bring your bag", "Sturdy polyester construction for lasting use", "Double top handles allow for easy carrying", "7.5in x 13in x 15in for a 6.3gal capacity"]}, {"id": "14897273", "keyword": "bag", "image_url": "https://target.scene7.com/is/image/Target/GUEST_4833a4d5-7312-4a6b-b6a5-2fc8e7bca751", "title": "Small Gift Bag Blue - Spritz&#8482;", "price": "$1.50", "description": ["Small blue gift bag", "Perfect for baby showers, birthdays and more", "Add matching tissue paper for a classy finish"]}, {"id": "79773483", "keyword": "bag", "image_url": "https://target.scene7.com/is/image/Target/GUEST_729c7798-eb2d-43d9-92eb-d2e64797cab3", "title": "Small Reversible Tote Handbag - A New Day&#8482; Olive Green", "price_range": "$30.00", "price": "$30.00", "description": ["Small tote handbag brings a stylish update to your ensemble", "Crafted from sturdy material for lasting use", "Designed with tie closure to keep your items secure", "Reversible design lends functional flair to your wardrobe"], "image_backup": ["https://target.scene7.com/is/image/Target/GUEST_69b939d7-66b3-46c7-823a-a852acd51a38", "https://target.scene7.com/is/image/Target/GUEST_c15dca5b-4707-4f2d-9a36-36eb323697f6"]}, {"id": "81549589", "keyword": "bag", "image_url": "https://target.scene7.com/is/image/Target/GUEST_7a33f3d5-b0ed-4b94-aaa1-e6f144ac3431", "title": "Addison Crossbody Bag - Universal Thread&#8482; Olive Green", "price_range": "$19.99 - $20.00", "price": "$20.00", "description": ["Universal Thread small crossbody bag complements your everyday, casual looks", "Adjustable crossbody strap lets you create the right look and fit", "Interior and exterior pockets keep your items organized and within easy reach", "Zipper closure along the top secures your belongings"], "image_backup": ["https://target.scene7.com/is/image/Target/GUEST_27b94528-f5f3-4b53-bd83-84b3201a23d7", "https://target.scene7.com/is/image/Target/GUEST_74c9e2f1-1922-4c55-a139-161888ee9fab"]}, {"id": "80634181", "keyword": "bag", "image_url": "https://target.scene7.com/is/image/Target/GUEST_4bae685e-c647-44b1-8732-c1a24739927d", "title": "Medium Rainbow Gift Bag - Spritz&#8482;", "price": "$1.50", "description": ["Medium-sized paper gift bag", "Sports a multicolored banded print", "Perfect for holiday and birthday gifting"], "image_backup": ["https://target.scene7.com/is/image/Target/GUEST_07a3b513-d4cd-4b45-b1a4-56e4383413ba", "https://target.scene7.com/is/image/Target/GUEST_868f54b4-3e77-4d7d-bb1a-47b3f1770c50"]}, {"id": "80880583", "keyword": "bag", "image_url": "https://target.scene7.com/is/image/Target/GUEST_53e0ecd1-50ff-4983-b4b8-24582ce7d1a6", "title": "Envelope Crossbody Bag - Universal Thread&#8482; Cognac", "price_range": "$15.00", "price": "$15.00", "description": ["Universal Thread crossbody bag brings subtle texture to your look", "Adjustable strap adjusts for the right fit and look every time", "Comes with magnetic closure to keep items securely inside", "Spacious interior with zipper pocket keeps essentials organized"], "image_backup": ["https://target.scene7.com/is/image/Target/GUEST_67275257-df94-4308-895b-7d3fa38df43e", "https://target.scene7.com/is/image/Target/GUEST_cabfd5f3-5da9-4b64-bb97-3f56a51e05f5"]}, {"id": "76422134", "keyword": "bag", "image_url": "https://target.scene7.com/is/image/Target/GUEST_cefa0ef3-8f61-47b3-842d-923337965587", "title": "Foil Star Dotted Medium Gift Bag Gray - Spritz&#8482;", "price": "$3.50", "description": ["Add flair to your presents with this elegant gift bag", "Understated yet glamorous design", "Perfect for a variety of occasions", "Great size for larger presents"]}, {"id": "80880630", "keyword": "bag", "image_url": "https://target.scene7.com/is/image/Target/GUEST_9377ed7a-f807-45ef-9102-df2dc08adead", "title": "Large Tote Handbag - Universal Thread&#8482; Cognac", "price_range": "$25.50 - $30.00", "price": "$30.00", "description": ["Universal Thread zip tote bag makes a great choice for work or travel", "Roomy main compartment for carrying your essentials", "Top zipper helps keep items from falling out", "Double top straps for comfy carrying over your shoulder", "Exterior slip pocket plus interior zip and accessory pockets for easy organization"], "image_backup": ["https://target.scene7.com/is/image/Target/GUEST_43567813-c76f-470b-9c55-ba3e6dcef53b", "https://target.scene7.com/is/image/Target/GUEST_07abf853-8568-412c-8d6b-87b34588d119"]}, {"id": "81538903", "keyword": "bag", "image_url": "https://target.scene7.com/is/image/Target/GUEST_d060c13a-6bbf-4881-b8f6-d8558f606a52", "title": "Square Backpack - Wild Fable&#8482; Black", "price_range": "$17.00 - $20.00", "price": "$20.00", "description": ["Women\u2019s square backpack", "Main zippered compartment and front zip pocket", "Interior compartment and zip pocket keep items organized", "Adjustable straps help you find the right fit"], "image_backup": ["https://target.scene7.com/is/image/Target/GUEST_8184d6bd-6091-4d6e-b8b4-4c355122ee4b", "https://target.scene7.com/is/image/Target/GUEST_e3cfb6d6-8a7d-4ac1-b623-255e4f1a22cb", "https://target.scene7.com/is/image/Target/GUEST_82f13c5d-c115-4cb4-8757-a071a4617ca5"]}, {"id": "54209470", "keyword": "bag", "image_url": "https://target.scene7.com/is/image/Target/GUEST_4a69d6c9-e4ae-47c8-8386-eccbd89378b0", "title": "Small Striped Gift Bags Pastel Lavender - Spritz&#8482;", "price": "$1.50", "description": ["Paper gift bag keeps gifting easy for any occasion", "Vertical stripes pattern lends an exciting touch to your gift", "Makes an easy alternative to wrapping paper", "Perfect for holding a variety of gift items"]}, {"id": "79773496", "keyword": "bag", "image_url": "https://target.scene7.com/is/image/Target/GUEST_19433f1c-0e5d-4dea-85bf-0f15f4dd0c88", "title": "Quilted Boxy Crossbody Bag - A New Day&#8482; Black", "price_range": "$25.50 - $30.00", "price": "$30.00", "description": ["Boxy crossbody bag updates your accessory collection", "Turn key closure helps keep your essentials secure", "Spacious interior with slip and zip pocket for easy organization", "Perfect size for carrying everyday essentials"], "image_backup": ["https://target.scene7.com/is/image/Target/GUEST_a444470e-e817-489d-9804-d0d7257d7897", "https://target.scene7.com/is/image/Target/GUEST_a5887de3-17b3-4600-9cb6-52b67b6a6684"]}, {"id": "81549578", "keyword": "bag", "image_url": "https://target.scene7.com/is/image/Target/GUEST_3c070a31-306e-4f85-b2fa-064689f1122d", "title": "Striped Soft Utility Square Backpack - Universal Thread&#8482; Black/White", "price_range": "$29.75 - $35.00", "price": "$35.00", "description": ["Universal Thread utility backpack with plenty of storage space and style", "Designed with double top handle and shoulder straps to carry as tote or backpack", "Interior laptop pocket, phone pocket and zip pocket for added organization", "Exterior zip and slip pockets to stash items you want in easy reach", "Cotton shell with faux leather top handles for stylish contrast"], "image_backup": ["https://target.scene7.com/is/image/Target/GUEST_4b907e7a-7179-477f-a695-b65fbe3e1d53", "https://target.scene7.com/is/image/Target/GUEST_5a4fac12-062f-4c0f-a027-0321913c94c1", "https://target.scene7.com/is/image/Target/GUEST_f6d7a820-084f-4897-9d62-c6c07aced827"]}, {"id": "76422138", "keyword": "bag", "image_url": "https://target.scene7.com/is/image/Target/GUEST_d397fd9a-af83-43e4-81b4-f12b8a1a243b", "title": "Small Hotstamp Dots And Star Gift Bag Gray - Spritz&#8482;", "price": "$1.50", "description": ["Add flair to your presents with this elegant gift bag", "Understated yet glamorous design", "Perfect for a variety of occasions"]}]